gpax/__init__.py
gpax/_version.py
gpax/hypo.py
gpax/acquisition/__init__.py
gpax/acquisition/acquisition.py
gpax/acquisition/base_acq.py
gpax/acquisition/batch_acquisition.py
gpax/acquisition/optimize.py
gpax/acquisition/penalties.py
gpax/kernels/__init__.py
gpax/kernels/kernels.py
gpax/kernels/mtkernels.py
gpax/models/__init__.py
gpax/models/bnn.py
gpax/models/corgp.py
gpax/models/dkl.py
gpax/models/gp.py
gpax/models/hskgp.py
gpax/models/ibnn.py
gpax/models/linreg.py
gpax/models/mngp.py
gpax/models/mtgp.py
gpax/models/sparse_gp.py
gpax/models/spm.py
gpax/models/uigp.py
gpax/models/vgp.py
gpax/models/vi_ibnn.py
gpax/models/vi_mtdkl.py
gpax/models/vidkl.py
gpax/models/vigp.py
gpax/priors/__init__.py
gpax/priors/priors.py
gpax/utils/__init__.py
gpax/utils/fn.py
gpax/utils/utils.py
gpax-0.1.9.dist-info/licenses/LICENSE
gpax-0.1.9.dist-info/WHEEL
gpax-0.1.9.dist-info/METADATA
gpax-0.1.9.dist-info/RECORD
