Metadata-Version: 2.4
Name: gpax
Version: 0.1.9
Summary: Gaussian processes in NumPyro and JAX
Author-email: Maxim Ziatdinov <maxim.ziatdinov@ai4microcopy.com>
Requires-Python: >=3.9
Classifier: Programming Language :: Python
Classifier: Development Status :: 3 - Alpha
Classifier: Intended Audience :: Science/Research
Classifier: Operating System :: POSIX :: Linux
Classifier: Operating System :: MacOS :: MacOS X
Classifier: Topic :: Scientific/Engineering
License-File: LICENSE
Requires-Dist: matplotlib>=3.1.1
Requires-Dist: jax>=0.6.2
Requires-Dist: jaxlib>=0.6.2
Requires-Dist: numpyro>=0.18.0
Requires-Dist: dm-haiku>=0.0.14
Requires-Dist: jaxopt>=0.8.5
Requires-Dist: flax>=0.10.7
Requires-Dist: flake8 ; extra == "test"
Requires-Dist: jaxlib ; extra == "test"
Requires-Dist: pytest ; extra == "test"
Requires-Dist: pytest-cov ; extra == "test"
Provides-Extra: test
